google_console/__init__.py
google_console/_base.py
google_console/_pipeline.py
google_console/_utils.py
google_console/scopes.py
google_console/drive/__init__.py
google_console/drive/_about.py
google_console/drive/_base.py
google_console/drive/_changes.py
google_console/drive/_channels.py
google_console/drive/_comments.py
google_console/drive/_drives.py
google_console/drive/_files.py
google_console/drive/_mixin.py
google_console/drive/_permissions.py
google_console/drive/_replies.py
google_console/drive/_revisions.py
google_console/drive/drive.py
google_console/gmail/__init__.py
google_console/gmail/_base.py
google_console/gmail/_drafts.py
google_console/gmail/_history.py
google_console/gmail/_labels.py
google_console/gmail/_messages.py
google_console/gmail/_messages_attachment.py
google_console/gmail/_mixin.py
google_console/gmail/_settings.py
google_console/gmail/_settings_delegates.py
google_console/gmail/_settings_filters.py
google_console/gmail/_settings_forwardingAddresses.py
google_console/gmail/_settings_sendAs.py
google_console/gmail/_settings_sendAs_smimeInfo.py
google_console/gmail/_threads.py
google_console/gmail/_users.py
google_console/gmail/gmail.py
google_console/photos/__init__.py
google_console/photos/_albums.py
google_console/photos/_base.py
google_console/photos/_mediaItems.py
google_console/photos/_mixin.py
google_console/photos/_sharedAlbums.py
google_console/photos/_utils.py
google_console/photos/photos.py
google_console/youtube/__init__.py
google_console/youtube/_base.py
google_console/youtube/_mixin.py
google_console/youtube/youtube.py
google_console-0.0.5.dist-info/METADATA
google_console-0.0.5.dist-info/WHEEL
google_console-0.0.5.dist-info/top_level.txt
google_console-0.0.5.dist-info/RECORD
