Metadata-Version: 2.1
Name: google-console
Version: 0.0.5
Summary: A set of Python modules for Google Cloud Console.
Home-page: https://pypi.org/project/google-console/
Maintainer: MLnAi Lab
Requires-Python: >=3.7
Requires-Dist: google-api-python-client (==1.12.11)
Requires-Dist: google-auth-httplib2 (==0.0.4)
Requires-Dist: google-auth-oauthlib (==0.4.6)
